{
  "name": "ai-input-13",
  "type": "registry:component",
  "dependencies": [
    "lucide-react"
  ],
  "registryDependencies": [
    "textarea"
  ],
  "files": [
    {
      "type": "registry:component",
      "content": "\"use client\";\n\nimport { ArrowRight } from \"lucide-react\";\nimport { useState } from \"react\";\nimport { Textarea } from \"@/components/ui/textarea\";\nimport { cn } from \"@/lib/utils\";\nimport { useAutoResizeTextarea } from \"@/hooks/use-auto-resize-textarea\";\n\ninterface SidebarSection {\n    title: string;\n    subtitle: string;\n    count: number;\n    items: string[];\n}\n\nexport default function AIInput_13() {\n    const [value, setValue] = useState(\"\");\n    const { textareaRef, adjustHeight } = useAutoResizeTextarea({\n        minHeight: 40,\n        maxHeight: 200,\n    });\n\n    const sidebarSections: SidebarSection[] = [\n        {\n            title: \"Saved Tools\",\n            subtitle: \"Most used\",\n            count: 12,\n            items: [\"Translate to French\", \"Summarize Text\", \"Generate Title\"],\n        },\n        {\n            title: \"History\",\n            subtitle: \"Past chats\",\n            count: 24,\n            items: [\n                \"API Integration Help\",\n                \"Debugging Assistant\",\n                \"Code Review Session\",\n            ],\n        },\n    ];\n\n    const handleKeyDown = (e: React.KeyboardEvent<HTMLTextAreaElement>) => {\n        if (e.key === \"Enter\" && !e.shiftKey) {\n            e.preventDefault();\n            setValue(\"\");\n            adjustHeight(true);\n        }\n    };\n    return (\n        <div className=\"w-full py-4\">\n            <div className=\"flex flex-col gap-4\">\n                <div className=\"bg-black/5 dark:bg-white/5 rounded-xl\">\n                    <div className=\"relative px-2 py-2\">\n                        <Textarea\n                            id=\"ai-input-13\"\n                            value={value}\n                            placeholder=\"Type your message...\"\n                            className={cn(\n                                \"w-full rounded-xl px-4 border-none resize-none bg-transparent focus-visible:ring-0 focus-visible:ring-offset-0 dark:text-white placeholder:text-black/70 dark:placeholder:text-white/70\",\n                                \"min-h-[40px]\"\n                            )}\n                            ref={textareaRef}\n                            onKeyDown={handleKeyDown}\n                            onChange={(e) => {\n                                setValue(e.target.value);\n                                adjustHeight();\n                            }}\n                        />\n\n                        <button\n                            type=\"button\"\n                            className=\"absolute right-3 top-1/2 -translate-y-1/2 rounded-xl bg-black/5 dark:bg-white/5 p-1\"\n                        >\n                            <ArrowRight\n                                className={cn(\n                                    \"w-4 h-4 dark:text-white\",\n                                    value ? \"opacity-100\" : \"opacity-30\"\n                                )}\n                            />\n                        </button>\n                    </div>\n                </div>\n\n                <div className=\"flex justify-center gap-4\">\n                    {sidebarSections.map((section) => (\n                        <div\n                            key={section.title}\n                            className=\"bg-black/5 dark:bg-white/5 rounded-xl p-3 flex-1\"\n                        >\n                            <div className=\"flex justify-between items-start mb-2\">\n                                <div>\n                                    <h3 className=\"font-semibold text-sm dark:text-white\">\n                                        {section.title}\n                                    </h3>\n                                    <p className=\"text-xs text-black/60 dark:text-white/60\">\n                                        {section.subtitle}\n                                    </p>\n                                </div>\n                                <span className=\"text-xs text-black/50 dark:text-white/50 ml-2\">\n                                    {section.count}\n                                </span>\n                            </div>\n\n                            <div className=\"space-y-2 mt-2\">\n                                {section.items.map((item) => (\n                                    <div\n                                        key={item}\n                                        className=\"text-xs text-black/60 hover:text-black dark:text-white/60 dark:hover:text-white cursor-pointer transition-colors\"\n                                    >\n                                        {item}\n                                    </div>\n                                ))}\n                            </div>\n                        </div>\n                    ))}\n                </div>\n            </div>\n        </div>\n    );\n}\n",
      "path": "/components/apexUi/ai-input/ai-input-13",
      "target": "components/apexUi/ai-input-13"
    },
    {
      "type": "registry:hook",
      "content": "\r\n\r\nimport { useEffect, useRef, useCallback } from \"react\";\r\n\r\ninterface UseAutoResizeTextareaProps {\r\n    minHeight: number;\r\n    maxHeight?: number;\r\n}\r\n\r\nexport function useAutoResizeTextarea({\r\n    minHeight,\r\n    maxHeight,\r\n}: UseAutoResizeTextareaProps) {\r\n    const textareaRef = useRef<HTMLTextAreaElement>(null);\r\n\r\n    const adjustHeight = useCallback(\r\n        (reset?: boolean) => {\r\n            const textarea = textareaRef.current;\r\n            if (!textarea) return;\r\n\r\n            if (reset) {\r\n                textarea.style.height = `${minHeight}px`;\r\n                return;\r\n            }\r\n\r\n            // Temporarily shrink to get the right scrollHeight\r\n            textarea.style.height = `${minHeight}px`;\r\n\r\n            // Calculate new height\r\n            const newHeight = Math.max(\r\n                minHeight,\r\n                Math.min(\r\n                    textarea.scrollHeight,\r\n                    maxHeight ?? Number.POSITIVE_INFINITY\r\n                )\r\n            );\r\n\r\n            textarea.style.height = `${newHeight}px`;\r\n        },\r\n        [minHeight, maxHeight]\r\n    );\r\n\r\n    useEffect(() => {\r\n        // Set initial height\r\n        const textarea = textareaRef.current;\r\n        if (textarea) {\r\n            textarea.style.height = `${minHeight}px`;\r\n        }\r\n    }, [minHeight]);\r\n\r\n    // Adjust height on window resize\r\n    useEffect(() => {\r\n        const handleResize = () => adjustHeight();\r\n        window.addEventListener(\"resize\", handleResize);\r\n        return () => window.removeEventListener(\"resize\", handleResize);\r\n    }, [adjustHeight]);\r\n\r\n    return { textareaRef, adjustHeight };\r\n}\r\n",
      "path": "/hooks/use-auto-resize-textarea",
      "target": "hooks/use-auto-resize-textarea"
    }
  ]
}